Workbook

Sheet How to use
A1: Peopleopslab — statutory verification worksheet
A3: Why this exists
A4: GO_LIVE.md D6 makes a payroll professional's sign-off a gate on real client data. This worksheet is that sign-off in a form an auditor can read a year from now.
A6: What to do
A7: 1. Fill every YELLOW cell. Nothing else is yellow, so that is the whole instruction.
A8: 2. 'Correct?' takes Y or N. Leave it blank if you could not verify it — blank is an honest answer and the Sign-off tab counts it separately.
A9: 3. On any N, put the right figure in 'Corrected value' and the date it took effect in 'Effective from'.
A10: 4. Cite your source. 'Finance Act 2026 s.2' or a gazette number — not 'checked online'.
A11: 5. Sign the Sign-off tab last. It counts the other tabs automatically.
A13: Order of work — highest value first
A14: Income tax FY 2026-27 covers the year currently being billed and is one Finance Act. Do it first; it is an afternoon. PT and LWF are 22 and 15 separate state schedules and can follow.
A16: What is NOT in this worksheet
... A25: Correct? = N | Corrected value = 20000 | Effective from = 2026-04-01 | Source = Karnataka PT (Amendment) Act 2026, Gazette 14-Mar-2026 | Reviewer = RKS | Date = 2026-09-30

Sheet Income tax
A1: Income tax — FY 2026-27
A2: HIGHEST PRIORITY. This is the financial year currently being billed. The code asserts Budget 2026 carried FY 2025-26 forward unchanged — that assertion is the first thing to test.
A4: Parameter | B4: Regime | C4: Value in code | D4: Unit | E4: Where in code | F4: Correct? | G4: Corrected value | H4: Effective from | I4: Source cited by reviewer | J4: Reviewer initials | K4: Date checked | L4: Notes
A5: Slab up to 400,000 | B5: New Regime | C5: 0 | D5: rate (fraction) | E5: app/services/tax_year_defaults.py
A6: Slab up to 800,000 | B6: New Regime | C6: 0.05 | D6: rate (fraction) | E6: app/services/tax_year_defaults.py
A7: Slab up to 1,200,000 | B7: New Regime | C7: 0.1 | D7: rate (fraction) | E7: app/services/tax_year_defaults.py
A8: Slab up to 1,600,000 | B8: New Regime | C8: 0.15 | D8: rate (fraction) | E8: app/services/tax_year_defaults.py
A9: Slab up to 2,000,000 | B9: New Regime | C9: 0.2 | D9: rate (fraction) | E9: app/services/tax_year_defaults.py
A10: Slab up to 2,400,000 | B10: New Regime | C10: 0.25 | D10: rate (fraction) | E10: app/services/tax_year_defaults.py
A11: Slab up to no limit | B11: New Regime | C11: 0.3 | D11: rate (fraction) | E11: app/services/tax_year_defaults.py
A12: Standard deduction | B12: New Regime | C12: 75000 | D12: INR | E12: app/services/tax_year_defaults.py
A13: 87A rebate — income limit | B13: New Regime | C13: 1200000 | D13: INR | E13: app/services/tax_year_defaults.py
A14: 87A rebate — maximum | B14: New Regime | C14: 60000 | D14: INR | E14: app/services/tax_year_defaults.py
A15: 87A marginal relief applies | B15: New Regime | C15: Yes | D15: flag | E15: app/services/tax_year_defaults.py
A16: Surcharge up to 5,000,000 | B16: New Regime | C16: 0 | D16: rate (fraction) | E16: app/services/tax_year_defaults.py
A17: Surcharge up to 10,000,000 | B17: New Regime | C17: 0.1 | D17: rate (fraction) | E17: app/services/tax_year_defaults.py
A18: Surcharge up to 20,000,000 | B18: New Regime | C18: 0.15 | D18: rate (fraction) | E18: app/services/tax_year_defaults.py
A19: Surcharge up to above top band | B19: New Regime | C19: 0.25 | D19: rate (fraction) | E19: app/services/tax_year_defaults.py
A20: Chapter VI-A deductions allowed | B20: New Regime | C20: No | D20: flag | E20: app/services/tax_year_defaults.py
A21: Slab up to 250,000 | B21: Old Regime | C21: 0 | D21: rate (fraction) | E21: app/services/tax_year_defaults.py
A22: Slab up to 500,000 | B22: Old Regime | C22: 0.05 | D22: rate (fraction) | E22: app/services/tax_year_defaults.py
A23: Slab up to 1,000,000 | B23: Old Regime | C23: 0.2 | D23: rate (fraction) | E23: app/services/tax_year_defaults.py
A24: Slab up to no limit | B24: Old Regime | C24: 0.3 | D24: rate (fraction) | E24: app/services/tax_year_defaults.py
A25: Standard deduction | B25: Old Regime | C25: 50000 | D25: INR | E25: app/services/tax_year_defaults.py
A26: 87A rebate — income limit | B26: Old Regime | C26: 500000 | D26: INR | E26: app/services/tax_year_defaults.py
A27: 87A rebate — maximum | B27: Old Regime | C27: 12500 | D27: INR | E27: app/services/tax_year_defaults.py
A28: 87A marginal relief applies | B28: Old Regime | C28: No | D28: flag | E28: app/services/tax_year_defaults.py
A29: Surcharge up to 5,000,000 | B29: Old Regime | C29: 0 | D29: rate (fraction) | E29: app/services/tax_year_defaults.py
A30: Surcharge up to 10,000,000 | B30: Old Regime | C30: 0.1 | D30: rate (fraction) | E30: app/services/tax_year_defaults.py
A31: Surcharge up to 20,000,000 | B31: Old Regime | C31: 0.15 | D31: rate (fraction) | E31: app/services/tax_year_defaults.py
A32: Surcharge up to 50,000,000 | B32: Old Regime | C32: 0.25 | D32: rate (fraction) | E32: app/services/tax_year_defaults.py
A33: Surcharge up to above top band | B33: Old Regime | C33: 0.37 | D33: rate (fraction) | E33: app/services/tax_year_defaults.py
A34: Chapter VI-A deductions allowed | B34: Old Regime | C34: Yes | D34: flag | E34: app/services/tax_year_defaults.py
A35: Health & education cess | B35: Both | C35: 0.04 | D35: rate (fraction) | E35: app/services/tax_year_defaults.py

Sheet PF and ESIC
A1: Provident Fund and ESIC
A2: Central rates. These change rarely, but the PF wage ceiling has been under review for years and a change here moves every payslip in the country.
A4: Parameter | B4: Value in code | C4: Unit | D4: Where in code | E4: Correct? | F4: Corrected value | G4: Effective from | H4: Source cited by reviewer | I4: Reviewer initials | J4: Date checked | K4: Notes
A5: PF — employee contribution | B5: 0.12 | C5: rate (fraction) | D5: app/schemas/statutory_config.py
A6: PF — employer contribution | B6: 0.12 | C6: rate (fraction) | D6: app/schemas/statutory_config.py
A7: PF — EPS share of employer | B7: 0.0833 | C7: rate (fraction) | D7: app/schemas/statutory_config.py
A8: PF — EDLI | B8: 0.005 | C8: rate (fraction) | D8: app/schemas/statutory_config.py
A9: PF — admin charges | B9: 0.005 | C9: rate (fraction) | D9: app/schemas/statutory_config.py
A10: PF — wage ceiling from 01 Sep 2014 (G.S.R. 609(E), 22 August 2014) | B10: 15000 | C10: INR per month | D10: app/services/statutory_calendar.py
A11: PF — wage ceiling from 17 Sep 2026 (S.O. 5109(E), 17 September 2026; EPS amended by G.S.R. 847(E), 25 September 2026) | B11: 25000 | C11: INR per month | D11: app/services/statutory_calendar.py
A12: PF — month the ceiling changes is split by days (Sep 2026: 1–16 old, 17–30 new) | B12: Yes | C12: flag | D12: app/services/statutory_calendar.py
A13: PF — cap wage at ceiling by default | B13: Yes | C13: flag | D13: app/schemas/statutory_config.py
A14: ESIC — employee contribution | B14: 0.0075 | C14: rate (fraction) | D14: app/schemas/statutory_config.py
A15: ESIC — employer contribution | B15: 0.0325 | C15: rate (fraction) | D15: app/schemas/statutory_config.py
A16: PF — EPS cap and post-2014 joiner limit follow the wage ceiling (joiner: ceiling on joining date) | B16: Yes | C16: flag | D16: app/services/rule_engine_v2.py (PF-004)
A17: ESIC — eligibility ceiling | B17: 21000 | C17: INR per month | D17: app/schemas/statutory_config.py
A18: ESIC — contribution periods start (months); coverage lasts to period end, s.2(9) | B18: 4, 10 | C18: month numbers | D18: app/services/statutory_calendar.py
A19: Gratuity — accrual fraction | B19: 15/26 per year | C19: fraction of Basic+DA | D19: app/services/cost_model.py

Sheet Labour Codes
A1: Labour Codes — wage definition and gratuity
A2: In force from 21 November 2025. These values drive LC-001 and the gratuity checks (GRAT-002, GRAT-003, GRAT-005). Each company can change them under Configuration & admin → Income tax & thresholds.
A4: Parameter | B4: Value in code | C4: Unit | D4: Where in code | E4: Correct? | F4: Corrected value | G4: Effective from | H4: Source cited by reviewer | I4: Reviewer initials | J4: Date checked | K4: Notes
A5: Codes effective from | B5: 2025-11-21 | C5: date | D5: app/schemas/rule_thresholds.py
A6: Wage definition — exclusions cap | B6: 50 | C6: % of remuneration | D6: app/schemas/rule_thresholds.py
A7: Wage components (empty = PF-applicable) | B7: PF-applicable components | C7: component keys | D7: app/schemas/rule_thresholds.py
A8: One-off payments left out of the 50% test | B8: gratuity, leave_encashment, retrenchment_compensation, notice_pay, bonus, ex_gratia | C8: component keys | D8: app/schemas/rule_thresholds.py
A9: Fixed-term gratuity — minimum service | B9: 1 | C9: years (counted in days) | D9: app/schemas/rule_thresholds.py
A10: Fixed-term employment types | B10: fixed term, fixed term employee, fixed term contract, ftc | C10: employment_type values | D10: app/schemas/rule_thresholds.py
A11: Gratuity — minimum service (others) | B11: 5 | C11: years (completed) | D11: app/schemas/rule_thresholds.py
A12: Gratuity — days of wages per year | B12: 15/26 | C12: fraction of monthly wages | D12: app/schemas/rule_thresholds.py
A13: PF on the deemed wages | B13: Reported by LC-001, not yet expected by STAT-001 | C13: policy | D13: app/schemas/rule_thresholds.py

Sheet PT by state
A1: Professional Tax — shipped state defaults
A2: 22 states, each amending on its own timetable. Source stated in code: Simpliance e-Library, verified late-2025 / early-2026. Check the states your clients actually operate in first.
A4: State | B4: Wage from | C4: Wage to | D4: Amount | E4: Frequency | F4: Gender | G4: Months | H4: Effective from | I4: Source stated in code | J4: Correct? | K4: Corrected value | L4: Effective from | M4: Source cited by reviewer | N4: Reviewer initials | O4: Date checked | P4: Notes
A5: Andhra Pradesh | B5: 0 | C5: 15000 | D5: 0 | E5: monthly | F5: ALL | G5: all | H5: — | I5: — no source cited —
A6: Andhra Pradesh | B6: 15001 | C6: 20000 | D6: 150 | E6: monthly | F6: ALL | G6: all | H6: — | I6: — no source cited —
A7: Andhra Pradesh | B7: 20001 | C7: 99999999 | D7: 200 | E7: monthly | F7: ALL | G7: all | H7: — | I7: — no source cited —
A8: Assam | B8: 0 | C8: 15000 | D8: 0 | E8: monthly | F8: ALL | G8: all | H8: — | I8: — no source cited —
A9: Assam | B9: 15001 | C9: 25000 | D9: 180 | E9: monthly | F9: ALL | G9: all | H9: — | I9: — no source cited —
A10: Assam | B10: 25001 | C10: 99999999 | D10: 208 | E10: monthly | F10: ALL | G10: all | H10: — | I10: — no source cited —
A11: Bihar | B11: 0 | C11: 300000 | D11: 0 | E11: yearly | F11: ALL | G11: all | H11: — | I11: — no source cited —
A12: Bihar | B12: 300001 | C12: 500000 | D12: 1000 | E12: yearly | F12: ALL | G12: all | H12: — | I12: — no source cited —
A13: Bihar | B13: 500001 | C13: 1000000 | D13: 2000 | E13: yearly | F13: ALL | G13: all | H13: — | I13: — no source cited —
A14: Bihar | B14: 1000001 | C14: 99999999 | D14: 2500 | E14: yearly | F14: ALL | G14: all | H14: — | I14: — no source cited —
A15: Chhattisgarh | B15: 0 | C15: 15000 | D15: 0 | E15: monthly | F15: ALL | G15: all | H15: — | I15: — no source cited —
A16: Chhattisgarh | B16: 15001 | C16: 20000 | D16: 150 | E16: monthly | F16: ALL | G16: all | H16: — | I16: — no source cited —
... A109: West Bengal | B109: 40001 | C109: 99999999 | D109: 200 | E109: monthly | F109: ALL | G109: all | H109: — | I109: — no source cited —

Sheet LWF by state
A1: Labour Welfare Fund — shipped state defaults
A2: 15 states. LWF amounts change quietly and with little notice, so treat an unchanged figure as unverified rather than confirmed.
A4: State | B4: Wage from | C4: Wage to | D4: Employee | E4: Employer | F4: Frequency | G4: Months | H4: Effective from | I4: Source stated in code | J4: Correct? | K4: Corrected value | L4: Effective from | M4: Source cited by reviewer | N4: Reviewer initials | O4: Date checked | P4: Notes
A5: Andhra Pradesh | B5: 0 | C5: 99999999 | D5: 30 | E5: 70 | F5: yearly | G5: 12 | H5: — | I5: — no source cited —
A6: Chhattisgarh | B6: 0 | C6: 99999999 | D6: 15 | E6: 45 | F6: half-yearly | G6: 6, 12 | H6: — | I6: — no source cited —
A7: Delhi | B7: 0 | C7: 99999999 | D7: 0.75 | E7: 2.25 | F7: half-yearly | G7: 6, 12 | H7: — | I7: — no source cited —
A8: Goa | B8: 0 | C8: 6500 | D8: 60 | E8: 180 | F8: half-yearly | G8: 6, 12 | H8: — | I8: — no source cited —
A9: Goa | B9: 6501 | C9: 99999999 | D9: 120 | E9: 360 | F9: half-yearly | G9: 6, 12 | H9: — | I9: — no source cited —
A10: Gujarat | B10: 0 | C10: 99999999 | D10: 6 | E10: 12 | F10: half-yearly | G10: 6, 12 | H10: — | I10: — no source cited —
A11: Haryana | B11: 0 | C11: 99999999 | D11: 31 | E11: 62 | F11: monthly | G11: all | H11: — | I11: — no source cited —
A12: Karnataka | B12: 0 | C12: 99999999 | D12: 50 | E12: 100 | F12: yearly | G12: 12 | H12: 2025-01-10 | I12: https://www.indiacode.nic.in/bitstream/123456789/7601/1/15_of_1965_%28e%29.pdf
A13: Kerala | B13: 0 | C13: 99999999 | D13: 50 | E13: 50 | F13: monthly | G13: all | H13: — | I13: — no source cited —
A14: Madhya Pradesh | B14: 0 | C14: 99999999 | D14: 10 | E14: 30 | F14: half-yearly | G14: 6, 12 | H14: — | I14: — no source cited —
A15: Maharashtra | B15: 0 | C15: 99999999 | D15: 25 | E15: 75 | F15: half-yearly | G15: 6, 12 | H15: 2024-03-18 | I15: https://bombayhighcourt.gov.in/bhc/libweb/legislation/acts/Stateact/2024acts/2024.25.pdf
A16: Odisha | B16: 0 | C16: 99999999 | D16: 20 | E16: 40 | F16: half-yearly | G16: 6, 12 | H16: — | I16: — no source cited —
... A21: West Bengal | B21: 3501 | C21: 99999999 | D21: 6 | E21: 18 | F21: half-yearly | G21: 6, 12 | H21: — | I21: — no source cited —

Sheet Sign-off
A1: Sign-off
A2: Counts update themselves from the tabs. Sign only when 'Not checked' is zero on every row you are accepting.
A4: Tab | B4: Rows | C4: Correct (Y) | D4: Wrong (N) | E4: Not checked | F4: Status
A5: Income tax | B5: 31 | C5: =COUNTIF('Income tax'!$F$5:$F$35,"Y") | D5: =COUNTIF('Income tax'!$F$5:$F$35,"N") | E5: =B5-C5-D5 | F5: =IF(E5>0,"INCOMPLETE",IF(D5>0,"CORRECTIONS NEEDED","ACCEPTED"))
A6: PF and ESIC | B6: 15 | C6: =COUNTIF('PF and ESIC'!$E$5:$E$19,"Y") | D6: =COUNTIF('PF and ESIC'!$E$5:$E$19,"N") | E6: =B6-C6-D6 | F6: =IF(E6>0,"INCOMPLETE",IF(D6>0,"CORRECTIONS NEEDED","ACCEPTED"))
A7: Labour Codes | B7: 9 | C7: =COUNTIF('Labour Codes'!$E$5:$E$13,"Y") | D7: =COUNTIF('Labour Codes'!$E$5:$E$13,"N") | E7: =B7-C7-D7 | F7: =IF(E7>0,"INCOMPLETE",IF(D7>0,"CORRECTIONS NEEDED","ACCEPTED"))
A8: PT by state | B8: 105 | C8: =COUNTIF('PT by state'!$J$5:$J$109,"Y") | D8: =COUNTIF('PT by state'!$J$5:$J$109,"N") | E8: =B8-C8-D8 | F8: =IF(E8>0,"INCOMPLETE",IF(D8>0,"CORRECTIONS NEEDED","ACCEPTED"))
A9: LWF by state | B9: 17 | C9: =COUNTIF('LWF by state'!$J$5:$J$21,"Y") | D9: =COUNTIF('LWF by state'!$J$5:$J$21,"N") | E9: =B9-C9-D9 | F9: =IF(E9>0,"INCOMPLETE",IF(D9>0,"CORRECTIONS NEEDED","ACCEPTED"))
A11: Total values | B11: =SUM(B5:B9) | E11: =SUM(E5:E9) | F11: =IF(E11>0,"NOT READY FOR CLIENT DATA","D6 SATISFIED")
A13: Slab rows citing a source | B13: 2 of 122
A14: Counted in slab rows, not states: PT is banded by wage, so 22 states become 105 rows, and LWF's 15 states become 17. 120 of those 122 rows carry no source in the code. They are not wrong — most predate the provenance field — but they are the rows to check first, because nothing records where they came from.
A18: Reviewer declaration
A19: Name
A20: Qualification / membership no.
A21: Firm
A22: Date
A23: Signature
A24: Labour Codes: PF expected on the deemed wages? (Y/N)
A26: I have checked the values marked Y against the sources I cited, and they are correct as at the date above.
